dynamispectra/Contacts.py
dynamispectra/Density.py
dynamispectra/Distance.py
dynamispectra/DistanceMatrix.py
dynamispectra/FractionSS.py
dynamispectra/Hbond.py
dynamispectra/Hydrophobic_contacts.py
dynamispectra/LigandAngle.py
dynamispectra/PCA.py
dynamispectra/PhiPsi.py
dynamispectra/Pressure.py
dynamispectra/RMSD.py
dynamispectra/RMSF.py
dynamispectra/Rg.py
dynamispectra/Rotamers.py
dynamispectra/SASA.py
dynamispectra/SecondaryStructure.py
dynamispectra/Temperature.py
dynamispectra/__init__.py
dynamispectra/cly.py
dynamispectra/ligand_density.py
dynamispectra/main.py
dynamispectra/saltbridge.py
dynamispectra-1.1.0.dist-info/METADATA
dynamispectra-1.1.0.dist-info/WHEEL
dynamispectra-1.1.0.dist-info/entry_points.txt
dynamispectra-1.1.0.dist-info/top_level.txt
dynamispectra-1.1.0.dist-info/RECORD
