Metadata-Version: 2.4
Name: DynamiSpectra
Version: 1.1.0
Summary: Scripts for Molecular dynamics analysis
Home-page: https://github.com/Conradoou/DynamiSpectra
Author: Iverson Conrado-Bezerra
Author-email: iverson.coonrado@gmail.com
License: MIT
Classifier: Programming Language :: Python :: 3
Classifier: License :: OSI Approved :: MIT License
Classifier: Operating System :: OS Independent
Requires-Python: >=3.7
Requires-Dist: numpy>=1.26.4
Requires-Dist: matplotlib>=3.8.4
Requires-Dist: pandas>=1.3.0
Requires-Dist: scipy>=1.13.1
Dynamic: author
Dynamic: author-email
Dynamic: classifier
Dynamic: description
Dynamic: description-content-type
Dynamic: home-page
Dynamic: license
Dynamic: requires-dist
Dynamic: requires-python
Dynamic: summary
